[
    {
        "key": "datr",
        "value": "WmRKavy6SdBw3-86qKs3WXp4",
        "domain": "facebook.com",
        "path": "/",
        "hostOnly": false,
        "creation": "2026-07-12T06:20:54.568Z",
        "lastAccessed": "2026-07-12T06:20:54.568Z"
    },
    {
        "key": "sb",
        "value": "WmRKakXruhUUzN-L2kJ71CL1",
        "domain": "facebook.com",
        "path": "/",
        "hostOnly": false,
        "creation": "2026-07-12T06:20:54.568Z",
        "lastAccessed": "2026-07-12T06:20:54.568Z"
    },
    {
        "key": "dpr",
        "value": "3.0234789848327637",
        "domain": "facebook.com",
        "path": "/",
        "hostOnly": false,
        "creation": "2026-07-12T06:20:54.568Z",
        "lastAccessed": "2026-07-12T06:20:54.568Z"
    },
    {
        "key": "locale",
        "value": "en_US",
        "domain": "facebook.com",
        "path": "/",
        "hostOnly": false,
        "creation": "2026-07-12T06:20:54.568Z",
        "lastAccessed": "2026-07-12T06:20:54.568Z"
    },
    {
        "key": "c_user",
        "value": "100004935707384",
        "domain": "facebook.com",
        "path": "/",
        "hostOnly": false,
        "creation": "2026-07-12T06:20:54.568Z",
        "lastAccessed": "2026-07-12T06:20:54.568Z"
    },
    {
        "key": "wd",
        "value": "891x1737",
        "domain": "facebook.com",
        "path": "/",
        "hostOnly": false,
        "creation": "2026-07-12T06:20:54.568Z",
        "lastAccessed": "2026-07-12T06:20:54.568Z"
    },
    {
        "key": "xs",
        "value": "50%3AA7aRVeCxJ1_5Ug%3A2%3A1783260642%3A-1%3A-1%3A%3AAcxxGcp74mulAPTZwnqr0Yf__TqYALyRXWY4xd4cgA",
        "domain": "facebook.com",
        "path": "/",
        "hostOnly": false,
        "creation": "2026-07-12T06:20:54.568Z",
        "lastAccessed": "2026-07-12T06:20:54.568Z"
    },
    {
        "key": "fr",
        "value": "17LklRvtPcWjxyccL.AWc4cckHWWt490JHR-Tylo7geOyzix2tmqxTQhwkQukZkbw6wog.BqUzG1..AAA.0.0.BqUzG4.AWcgz4enFTARC5UCgTgdt35rxu4",
        "domain": "facebook.com",
        "path": "/",
        "hostOnly": false,
        "creation": "2026-07-12T06:20:54.568Z",
        "lastAccessed": "2026-07-12T06:20:54.568Z"
    },
    {
        "key": "presence",
        "value": "C%7B%22t3%22%3A%5B%5D%2C%22utc3%22%3A1783837117764%2C%22v%22%3A1%7D",
        "domain": "facebook.com",
        "path": "/",
        "hostOnly": false,
        "creation": "2026-07-12T06:20:54.568Z",
        "lastAccessed": "2026-07-12T06:20:54.568Z"
    }
]
